pvspeaker/LICENSE
pvspeaker/__init__.py
pvspeaker/_pvspeaker.py
pvspeaker/lib/linux/x86_64/libpv_speaker.so
pvspeaker/lib/mac/arm64/libpv_speaker.dylib
pvspeaker/lib/mac/x86_64/libpv_speaker.dylib
pvspeaker/lib/raspberry-pi/cortex-a53/libpv_speaker.so
pvspeaker/lib/raspberry-pi/cortex-a53-aarch64/libpv_speaker.so
pvspeaker/lib/raspberry-pi/cortex-a72/libpv_speaker.so
pvspeaker/lib/raspberry-pi/cortex-a72-aarch64/libpv_speaker.so
pvspeaker/lib/raspberry-pi/cortex-a76/libpv_speaker.so
pvspeaker/lib/raspberry-pi/cortex-a76-aarch64/libpv_speaker.so
pvspeaker/lib/windows/amd64/libpv_speaker.dll
pvspeaker/lib/windows/arm64/libpv_speaker.dll
pvspeaker-1.0.5.dist-info/METADATA
pvspeaker-1.0.5.dist-info/WHEEL
pvspeaker-1.0.5.dist-info/top_level.txt
pvspeaker-1.0.5.dist-info/RECORD
